teko/__init__.py
teko/cli/__init__.py
teko/cli/cs_command.py
teko/cli/jira_command.py
teko/cli/main.py
teko/cli/oas_command.py
teko/helpers/__init__.py
teko/helpers/clog.py
teko/helpers/exceptions.py
teko/helpers/file_io.py
teko/models/__init__.py
teko/models/jira_export_test/__init__.py
teko/models/jira_export_test/storage.py
teko/models/jira_export_test/test_case.py
teko/models/jira_export_test/test_cycle.py
teko/models/jira_export_test/test_step.py
teko/models/jira_tool/__init__.py
teko/models/jira_tool/jira_testcase.py
teko/services/__init__.py
teko/services/jira/__init__.py
teko/services/jira/jira_service.py
teko/services/jira_export_test/__init__.py
teko/services/jira_export_test/test_case_service.py
teko/services/jira_export_test/test_cycle_service.py
teko/services/oas/__init__.py
teko/services/oas/oas_service.py
teko/services/oas/compare/__init__.py
teko/services/oas/compare/specification_diff.py
teko/templates/cycle.json
teko/templates/cycle.yaml
teko/templates/testcases.json
teko/templates/testcases.yaml
teko/templates/testcases_with_cycle_bundle.json
teko/templates/testcases_with_cycle_bundle.yaml
teko/test/__init__.py
teko/test/test_create_test_from_docstring.py
teko/utils/__init__.py
teko/utils/jira_export_test/__init__.py
teko/utils/jira_export_test/wraper.py
teko_export_test-0.1.1.dist-info/METADATA
teko_export_test-0.1.1.dist-info/WHEEL
teko_export_test-0.1.1.dist-info/entry_points.txt
teko_export_test-0.1.1.dist-info/top_level.txt
teko_export_test-0.1.1.dist-info/RECORD
