Metadata-Version: 2.1
Name: teko-export-test
Version: 0.1.1
Summary: Teko CLI tools
Home-page: https://git.teko.vn/vnpay-marketing-portal/teko-tools
Author: Thuc Nguyen
Author-email: thuc.nc@teko.vn
License: MIT
Download-URL: https://pypi.org/project/teko/
Keywords: Teko,Teko CLI tools
Platform: UNKNOWN
Requires-Dist: requests
Requires-Dist: jinja2
Requires-Dist: tabulate
Requires-Dist: typer
Requires-Dist: colorama
Requires-Dist: dataclasses-json
Requires-Dist: ruamel.yaml
Requires-Dist: python-dotenv
Requires-Dist: bs4
